{
    "c_id": "1522_1",
    "domain": 2,
    "source": 6,
    "source_spec": "['4492)', 'docx']",
    "creation_year": "null",
    "content": "치질은 전 세계적으로 수백만 명에게 영향을 미치는 흔한 항문 직장 질환입니다. 치질은 항문관 내 정상적인 혈관 구조인 치질 쿠션이 병적으로 확장되거나 하방으로 변위되면서 증상이 나타나는 상태를 말합니다. 이 치질 쿠션은 대변 조절에 중요한 역할을 하지만, 병적으로 확장되면 통증, 출혈, 탈출 등의 다양한 증상을 유발할 수 있습니다. 치질의 해부학적 및 생리학적 이해 치질 쿠션은 항문관 내에 위치한 혈관 조직, 평활근, 결합조직의 집합체로 구성되어 있습니다. 이 구조는 항문 괄약근의 정상적인 기능에 필수적이며, 특히 배변 중 고형, 액체, 가스를 구별하는 데 기여하여 대변 조절에 중요한 역할을 합니다. 내치질 내치질은 치상선 위에 위치하며 원주상피로 덮여 있어 체성 신경 분포가 없기 때문에 통증에 덜 민감합니다. 내치질은 항문관의 왼쪽 측면, 오른쪽 앞쪽, 오른쪽 뒤쪽에 위치하며, 이는 대변 조절을 돕는 주요 혈관 쿠션에 해당합니다. 외치질 외치질은 치상선 아래에 위치하며 편평상피로 덮여 있고 체성 신경 분포가 있어 통증에 매우 민감합니다. 외치질은 혈전증에 걸리기 쉬우며, 이는 급성 및 심한 통증을 초래할 수 있습니다. 치질의 병태생리 치질 질환의 발병은 정상적인 치질 쿠션이 병변으로 변하면서 증상을 유발하는 여러 복잡한 메커니즘을 포함합니다. 주요 메커니즘은 다음과 같습니다. 1. 미끄러지는 항문관 이론 치질은 Treitz 근육과 결합된 종근과 같은 지지 구조의 약화로 인해 치질 쿠션이 하방으로 변위되면서 발생한다고 여겨집니다. 이러한 약화는 무거운 물건을 들거나 만성 기침 등으로 복압이 증가할 때 악화됩니다. 이 이론은 내치질이 항문관 밖으로 탈출하여 증상성 탈출과 불편함을 유발하는 과정을 설명합니다. 2. 혈관 확장 및 혈역학적 변화 치질 조직은 동정맥 문합으로 이루어진 풍부한 혈관 네트워크를 가지고 있습니다. 치질의 병태생리에서 이러한 혈관은 동맥 유입의 증가와 정맥 유출의 감소로 인해 확장됩니다. 이는 장시간 앉아 있거나 저섬유질 식단, 임신 등 생활방식 요인에 의해 악화될 수 있습니다. 혈관 확장은 치질 쿠션을 확대시키고 탈출을 유발하여 출혈과 자극 같은 증상을 초래합니다. 3. 결합조직 퇴화 노화 및 항문관의 반복적인 외상은 치질 쿠션을 지탱하는 결합조직을 약화시킬 수 있습니다. 결합조직, 특히 콜라겐과 엘라스틴 섬유의 퇴화는 탄력성과 지지력을 상실하게 하여 치질 쿠션의 하강을 유발합니다. 결합조직 장애와 같은 유전적 요인은 조기에 더 심각한 치질 질환을 일으킬 수 있습니다. 4. 만성 염증 만성 염증은 치질 질환의 병태생리에 중요한 역할을 합니다. 염증 반응은 치질 조직의 탈출과 자극에 의해 유발되며, 염증 매개체의 방출로 증상이 악화됩니다. 이 염증은 점막 침식을 일으켜 직장 출혈을 초래하고, 점액의 지속적인 분비와 항문 주변 자극으로 인해 항문 가려움증을 유발할 수 있습니다. 5. 정맥 혈전증 외치질에서는 혈관 울혈과 기계적 스트레스의 결합으로 정맥 혈전증이 발생할 수 있습니다. 혈전증이 발생하면 치질 혈관 내에 혈전이 형성되며, 이는 급성 통증을 동반한 팽팽하고 압통이 있는 항문 주위 덩어리로 나타납니다. 치료하지 않으면 혈전성 치질은 궤양을 유발하여 추가 합병증을 초래할 수 있습니다. 치질의 임상적 특징 및 진단 치질의 증상은 내치질인지 외치질인지, 그리고 그 심각도에 따라 다릅니다. 주요 증상은 다음과 같습니다. 1. 직장 출혈 통증이 없는 직장 출혈은 내치질의 주요 증상입니다. 환자는 배변 후 화장지나 변기에서 밝은 빨간색 혈액을 발견하는 경우가 많습니다. 혈액은 일반적으로 대변을 덮고 있으며, 이는 혈액이 장 상부에서 발생하는 경우와 구별하는 데 도움을 줍니다. 그러나 심한 경우, 특히 치질이 탈출하거나 궤양이 생긴 경우 출혈이 더 심해질 수 있으며, 대장암이나 게실질환과 같은 다른 원인을 배제하기 위한 추가 진단 평가가 필요할 수 있습니다. 2. 치질 탈출 치질 탈출은 내치질이 항문 밖으로 돌출될 때 발생합니다. 탈출은 그 심각도에 따라 1도에서 4도로 분류됩니다. 1도: 출혈은 있지만 탈출되지 않은 치질. 2도: 배변 중 탈출하지만 자연스럽게 복원되는 치질. 3도: 배변 중 탈출하며 수동으로 복원해야 하는 치질. 4도: 복원되지 않으며 괴사 위험이 있는 치질. 3. 통증 및 불편감 통증은 주로 외치질과 관련이 있으며, 특히 혈전증이 발생한 경우 심합니다. 혈전증이 발생한 외치질 환자는 급성, 심한 통증을 경험하며, 이는 날카롭거나 타는 듯한 느낌으로 묘사됩니다. 종종 촉진 가능한 압통이 있는 항문 주위 덩어리가 동반됩니다. 반면, 내치질은 탈출 및 협착되지 않는 한 통증을 유발하지 않는 경우가 많습니다. 4. 가려움증 및 자극 항문 가려움증은 치질 환자들 사이에서 흔히 호소되는 증상입니다. 이는 탈출된 치질로 인한 점액 분비나 불완전한 항문 위생으로 인해 항문 주변 피부가 자극받아 발생합니다. 가려움증은 강렬하고 지속적일 수 있으며, 추가적인 자극과 불편감을 초래할 수 있습니다. 치질의 치료 치질 치료는 증상의 심각도, 치질의 등급, 환자의 개별적 요인을 고려한 맞춤형 접근이 필요합니다. 치료 옵션은 보존적 치료에서부터 고급 수술적 개입에 이르기까지 다양하며, 각각 특정 적응증과 결과를 가지고 있습니다. 보존적 치료 1. 식이 및 생활 습관 수정 고섬유질 식단: 섬유질 섭취 증가는 치질 관리의 기초입니다. 과일, 채소, 통곡물 등이 풍부한 고섬유질 식단은 대변을 부드럽게 하고 배변 시 힘주기를 줄여줍니다. 수분 섭취: 충분한 수분 섭취는 변비 예방 및 규칙적인 배변 촉진에 필수적입니다. 행동 수정: 변기에 오래 앉아 있지 말고, 배변 욕구가 있을 때 즉시 반응하도록 권장합니다. 2. 국소 및 약물 치료 국소 제제: 항염증 효과가 있는 스테로이드 크림과 연고는 염증 및 가려움증을 줄이는 데 도움을 줍니다. 경구 약물: 플라보노이드 계열의 약물은 혈관 보호, 항염증, 항산화 특성으로 치질 치료에 사용됩니다. 3. 좌욕 따뜻한 물에 좌욕하는 것은 치질과 관련된 불편감을 완화하는 간단하고 효과적인 방법입니다. 4. 변 완화제 및 완하제 변비를 예방하고 배변 시 힘주기를 줄이는 데 도움을 줍니다. 비수술적 치료 보존적 치료가 실패하거나 환자가 더 진행된 치질 질환을 나타낼 경우, 비수술적 치료가 필요할 수 있습니다. 고무 밴드 결찰술 경화요법 적외선 응고법 냉동치료 수술적 치료 심각한 치질 질환(3도 및 4도)을 가진 환자 또는 보존적 및 비수술적 치료에 반응하지 않는 환자의 경우, 수술적 개입이 필요할 수 있습니다. 전통적 치질 절제술 스테이플 치질 고정술 도플러 유도 치질 동맥 결찰술 치질 치료는 환자의 상태와 선호도에 따라 개별화되어야 하며, 적절한 치료를 통해 증상 완화와 삶의 질 향상이 가능합니다."
}