{
    "qa_id": 627731,
    "domain": 17,
    "q_type": 1,
    "question": "52세 여성이 2주 전부터 시작된 심한 피로, 두통, 근육통, 기침 및 호흡 곤란으로 응급실에 내원하였다. 환자는 이전에 폐 질환 병력이 없으며, 흡연력도 없다. 신체 검진에서 빈호흡, 빈맥, 청진 시 양쪽 폐의 수포음과 천명이 들렸다. 혈액 가스 분석에서 저산소증이 확인되었다. 흉부 X선 촬영에서는 양측 폐의 공기-공간 혼탁이 관찰되었고, 고해상도 CT에서는 양측 폐의 간유리 음영, 견인 기관지 확장증, 공기 공간의 응축 및 구조적 왜곡이 보였다. 이 환자의 상태는 특발성 폐섬유화증으로 의심된다. 다음 중 이 환자의 질환에 대한 가장 적절한 치료법은?  \n1) 광범위 항생제 치료  \n2) 항결핵제 치료  \n3) 글루코코르티코이드 및 면역억제제 투여  \n4) 항섬유화제 투여 및 산소 치료  \n5) 폐 이식 고려",
    "answer": "4) 항섬유화제 투여 및 산소 치료"
}