{
    "qa_id": 426,
    "domain": 17,
    "q_type": 1,
    "question": "80세 여자가 1-2주 전부터 움직이면 숨이 찬 증상으로 병원에 왔다. 1주 전 피곤하여 수액주사를 맞은 후 증상이 시작되었다. 환자는 10년 전부터 고혈압으로 칼슘채널차단제를 복용 중이다. 활력징후는 혈압 131/70mmHg, 맥박 67회/분, 호흡 24회/분, 체온 36.6℃이다. 가슴 청진에서 제3심음이 들리며 심장 끝에서 4/6도의 수축기 심잡음이 들리고, 양쪽 등 아랫부분에서 거품소리가 들린다. 양쪽 정강뼈 앞 오목부종이 관찰된다. 가슴 X선 사진에서는 양측 폐문 주변의 음영 증가(Bilateral Perihilar Opacities)가 관찰되며, 심전도는 정상이다. 이 환자에게 가장 적절한 치료는 무엇인가?  \n1) 도부타민  \n2) 이바브라딘  \n3) 푸로세미드  \n4) 라미프릴  \n5) 카르베딜롤",
    "answer": "3) 푸로세미드"
}