{
    "qa_id": 625687,
    "domain": 5,
    "q_type": 3,
    "question": "30세 여성이 손톱 주변의 통증과 발적을 주소로 내원하였다. 환자는 최근 손톱 주위의 큐티클을 자주 물어뜯었으며, 몇 주 전부터 해당 부위에 통증과 부종이 나타나기 시작했다고 한다. 신체 검진에서는 손톱 주변이 빨갛고 부풀어 있으며, 압통이 있었다. 환자는 손을 물에 자주 담그는 직업을 가지고 있었다. 이 환자의 가장 가능성 높은 진단명과 그 원인, 그리고 적절한 치료 방법을 설명하시오.",
    "answer": "이 환자의 진단은 만성 손톱주위염(Chronic paronychia)이다. 만성 손톱주위염의 주요 원인은 Candida albicans와 같은 진균 감염이며, 손을 물에 자주 담그는 환경이 위험 요인으로 작용할 수 있다. 치료는 항진균제를 국소적으로 적용하거나 필요 시 경구 항진균제를 사용하는 것이 적절하다. 또한, 손톱 주위의 피부를 보호하고 물에 장시간 노출되지 않도록 주의하며, 큐티클을 물어뜯는 습관을 교정하는 것이 중요하다."
}