{
    "c_id": "53299_1",
    "domain": 2,
    "source": 1,
    "source_spec": "Cochrane Library",
    "creation_year": "2016",
    "content": "글루타민은 조건부 필수 아미노산으로, 신체 내에서 합성이 가능하지만 대사적 스트레스 상태에서는 조직의 요구를 충족시키기에 부족할 수 있습니다. 글루타민 섭취가 중증 성인 환자의 임상적 결과를 개선한다는 근거가 존재합니다. 이 연구에서는 Cochrane Neonatal Review Group의 표준 검색 전략을 사용하여 관련 데이터를 수집하였습니다. Cochrane 신생아 검토 그룹의 표준 방법론을 통해 데이터를 추출하였으며, 두 명의 검토자가 임상 시험의 질과 데이터 추출 과정을 독립적으로 평가하였습니다. 총 2,877명의 조산아가 참여한 12건의 무작위 대조 시험이 확인되었습니다. 이 중 6건의 임상 시험에서는 장내 글루타민 보충이, 나머지 6건의 임상 시험에서는 비경구적 글루타민 보충이 평가되었습니다. 임상 시험의 방법론적 질은 대체로 양호한 것으로 평가되었습니다. 그러나 글루타민 보충이 신생아의 주요 이환율, 예를 들어 패혈증이나 괴사성 장염과 같은 침습성 감염의 발생률에 유의미한 영향을 미친다는 증거는 발견되지 않았습니다. 결론적으로, 현재 이용 가능한 임상 시험 데이터는 글루타민 보충이 조산아에게 중요한 혜택을 제공한다는 근거를 제시하지 못합니다."
}