{
    "c_id": "32443_1",
    "domain": 2,
    "source": 1,
    "source_spec": "KJM",
    "creation_year": "2005",
    "content": "46세 여성이 좌측 무릎 통증을 주소로 내원하였습니다. 환자는 1년 전부터 좌측 무릎의 간헐적 통증을 호소하며 인근 병원에서 진통제 및 약물 주입 치료를 받았으나 증상이 호전되지 않아 추가 검사를 위해 내원하였습니다. 과거력으로는 2004년 갑상선 낭종으로 갑상선 전절제술을 받았고, 2006년 췌장 양성 낭종으로 원위부 췌장절제술을 시행받은 이력이 있으며, 고혈압으로 칼슘 채널 차단제를 복용 중이었습니다. 진찰 결과, 환자의 활력 징후는 안정적이었으며, 복부는 편평하고 압통이나 반발통이 없었고, 직장 수지 검사에서도 만져지는 종괴는 없었습니다. 양측 무릎에 대한 진찰에서 운동 제한, 압통, 발적 소견은 관찰되지 않았습니다. 검사실 소견으로는 혈색소 11.6 g/dL, 백혈구 6,490/mm², 혈소판 145,000/mm²로 나타났으며, 혈청 생화학 검사에서는 ALP 419 IU/L, LDH 325 IU/L, 종양 표지자인 CEA가 30.04 ng/mL로 상승되어 있었습니다. 영상의학적 검사에서 좌측 무릎 전산화 단층 촬영상 근위부 경골에 8.3 x 5.3 cm 크기의 종괴가 관찰되었으며, 종괴 주변에 종양 침윤을 시사하는 비정상 신호 변화가 확인되었습니다. 복부 전산화 단층 촬영에서는 직장암이 의심되었고, 주변 림프절 전이가 동반된 상태였으나 간이나 폐와 같은 다른 장기 전이는 관찰되지 않았습니다. 좌측 무릎 종괴에 대해 경피세침생검을 시행한 결과, 조직학적으로 선암으로 진단되었습니다. 대장내시경 검사에서는 항문연에서 7 cm 떨어진 직장에 3 cm 크기의 직장암이 확인되었으며, 조직검사 결과 슬관절 종괴와 동일한 선암으로 진단되었습니다. 환자는 직장암의 슬관절 전이로 진단받고 항암화학요법(FOLFOX)을 6회 시행받았습니다. 치료 후 평가에서 직장의 병변은 부분 관해를 보였으며, 림프절 비대는 감소하였으나 슬관절 병변은 크기가 약간 감소(8.3 cm에서 7.5 cm)하였으나 안정성 병변으로 평가되었습니다. 환자는 지속적인 통증을 호소하였고, Mirel's scoring system에서 9점으로 병적 골절의 위험도가 높아 정형외과와 협진 후 고식적 전이 병변 절제술을 시행하였습니다. 수술 후 환자는 추가로 5회의 FOLFOX 항암화학요법을 시행받았으며, 현재 부분적 관해 상태에서 원발 병소와 림프절 전이에 대한 수술적 절제술을 계획 중입니다. 대장암의 골 전이는 주로 척추에 발생하며, 사지로의 전이는 매우 드문 것으로 알려져 있습니다. 본 증례는 슬관절 전이가 초기 증상으로 나타난 국내 첫 사례로, 항암화학요법에 대한 반응이 원발 병소와 림프절에 비해 슬관절 병변에서 떨어지는 양상을 보였습니다. 이는 원위부 골의 혈류가 적어 약제 전달이 제한되었을 가능성과 관련이 있을 것으로 추정되며, 향후 추가적인 연구가 필요합니다."
}