{
    "c_id": "33036_1",
    "domain": 2,
    "source": 1,
    "source_spec": "KJM",
    "creation_year": "2006",
    "content": "호지킨 림프종의 치료는 20세기 초 방사선 치료 기술과 화학요법의 발전으로 인해 큰 성과를 이루었으며, 특히 조기 병기 환자의 약 90%가 장기 생존이 가능해졌습니다. 하지만 조기 병기 환자들조차도 질병의 다양성과 환자 개개인의 특성으로 인해 동일한 치료 접근법을 적용할 수는 없습니다. 또한, 장기 생존율이 높아짐에 따라 치료로 인한 지연성 부작용이 중요한 문제로 대두되고 있습니다. 호지킨 림프종의 병기는 Ann Arbor 병기 체계를 기반으로 나뉘며, I기와 II기는 조기 병기로, IIB기 이상은 진행 병기로 분류됩니다. 조기 병기 환자들 중에서도 예후는 다양하며, B 증상, ESR 상승, 림프구역 침윤, 림프절 외 종양, 고령, 큰 종격동 종양 등이 불량한 예후 인자로 보고되었습니다. 조기 병기 호지킨 림프종의 치료는 방사선 요법과 화학요법의 병합으로 이루어지며, 방사선 요법만으로는 완치가 어려운 경우가 많습니다. 과거에는 광범위 방사선 요법이 사용되었으나, 이로 인한 이차 암종 및 림프종 외 사망률 증가로 인해 현재는 최소한의 방사선 조사와 화학요법을 병합하는 복합 요법이 주로 사용됩니다. 예를 들어, ABVD 화학요법과 병변 부위 방사선 요법(IFRT)을 병합한 치료가 높은 생존율을 보이며 표준 치료로 자리 잡았습니다. 양호한 예후의 조기 병기 환자에서는 ABVD 2~4주기와 20~30 Gy의 방사선 요법이 효과적이며, 치료 강도를 낮추는 연구도 진행 중입니다. 예를 들어, GHSG HD10 연구에서는 ABVD 2주기와 20 Gy 방사선 요법이 새로운 표준 요법으로 제안되었습니다. 반면, 불량한 예후의 조기 병기 환자에서는 ABVD 4주기와 30 Gy 방사선 요법이 필요하며, 치료 강도를 조정하는 연구가 계속되고 있습니다. 치료의 지연성 부작용은 장기 생존 환자들에게 중요한 문제로, 갑상선 기능 저하, 이차 암종, 심장질환, 폐 섬유화 등이 포함됩니다. 방사선 치료는 폐암, 유방암, 심장질환의 위험을 증가시키며, 화학요법은 골수이형성 증후군 및 급성 백혈병의 발생과 관련이 있습니다. 특히, MOPP 요법은 ABVD 요법에 비해 이차 암종 발생률이 높습니다. 결론적으로, 조기 병기 호지킨 림프종의 치료는 높은 생존율을 보이는 성공적인 사례로, 현재의 연구 초점은 치료 효과를 유지하면서 지연성 부작용을 최소화하는 데 있습니다. 이를 위해 표준 화학요법 단독 치료, 최소한의 방사선 요법, 그리고 Interim PET 스캔을 활용한 개별화된 치료법 개발이 진행되고 있습니다."
}