{
    "c_id": "35936_1",
    "domain": 2,
    "source": 1,
    "source_spec": "KSEM",
    "creation_year": "2021",
    "content": "2015년 미국심장협회(American Heart Association) 심폐소생술 지침에서는 흉골 아래쪽 절반을 가슴 압박 위치로 권장하고 있습니다. 그러나 흉골 아래쪽 절반을 압박할 경우, 좌심실 유출로가 압박되어 체순환 및 폐순환에 적절하지 않을 수 있다는 보고가 있었습니다. 반면, 흉골-검상돌기 접합부(sterno-xiphoid junction) 근처를 압박하는 것이 좌심실을 더 효율적으로 압박할 수 있다는 연구 결과도 있습니다. 심장은 횡격막 위에 위치한 장기로, 횡격막의 위치 변화에 따라 심장의 위치도 변합니다. 따라서 심정지 환자에서 가슴 압박을 시행할 때, 복부 팽만으로 인한 횡격막 위치 변화를 고려해야 할 필요가 있습니다. 본 연구는 복부 팽만 유무에 따른 횡격막 위치 변화가 심장 및 간의 위치에 미치는 영향을 분석하고, 이를 바탕으로 적절한 가슴 압박 위치를 다중검출 컴퓨터 단층촬영(MDCT)을 통해 확인하고자 하였습니다. 연구 대상은 2013년 1월부터 2018년 6월까지 한 대학병원 응급의료센터에서 대동맥 박리증을 감별하기 위해 흉복부 MDCT를 시행받은 환자 중, 심장 위치에 영향을 미칠 수 있는 특정 조건(예: 술통 가슴, 다량의 혈흉, 결핵으로 손상된 폐 등)을 가진 9명을 제외한 58명이었습니다. 복부 팽만 여부는 흉골 아래쪽 절반의 중심부와 배꼽 주위의 높이를 비교하여 결정하였습니다. 복부 팽만군은 배꼽 주위가 흉골 아래쪽 절반의 중심부보다 높은 경우로 정의하였고, 비팽만군은 그렇지 않은 경우로 정의하였습니다. 심장의 위치는 좌심실 최대 직경(LVMD)이 관찰되는 위치를 기준으로 하였으며, 척추를 기준으로 점수화하여 분석하였습니다. 여섯 번째 흉추 상반부를 0점으로, 여섯 번째 흉추 하반부를 1점으로 하여 열 번째 흉추 하반부까지 점수를 부여하였습니다. 또한, LVMD 위치와 흉골 아래쪽 절반의 중심부 및 흉골 끝단까지의 거리를 측정하였습니다. 연구 결과, 복부 팽만군에서 LVMD 위치가 흉골 끝단보다 더 위로 상승하는 경향이 확인되었습니다. 남성의 경우 복부 팽만 유무에 따라 LVMD 위치와 관련된 변수들에 유의한 차이가 있었으나, 여성에서는 유의한 차이가 없었습니다. 이는 복부 팽만의 정도가 남성보다 여성에서 덜 심했기 때문일 가능성이 제기되었습니다. 가슴 압박의 효과적인 위치를 결정하기 위해서는 심실 부위를 직접 압박하여 심실 용적 변화를 유발하고, 이를 통해 수축기 혈류를 생성해야 합니다. 기존 연구에서는 흉골 하부를 압박하는 것이 적절하다고 보고되었으나, 흉골-검상돌기 접합부를 압박하는 것이 더 효율적일 수 있다는 제안도 있었습니다. 본 연구에서도 복부 팽만이 있는 경우 LVMD 위치가 기존 지침에서 제시된 가슴 압박 중간점보다 약 4cm 위에 위치하는 것으로 나타났습니다. 복부 팽만은 내장 지방 과다, 음식물 과다 섭취, 장내 가스 충만 등 다양한 원인에 의해 발생할 수 있으며, 이러한 원인에 따라 횡격막 위치 변화에 미치는 영향이 다를 수 있습니다. 그러나 본 연구에서는 복부 팽만의 원인을 세부적으로 구분하지 않았으며, 육안적으로 관찰되는 복부 팽만 유무만을 평가하였습니다. 본 연구의 제한점으로는 단일 기관에서 소규모 환자를 대상으로 진행되었기 때문에 전체 인구를 대표하기 어렵다는 점, 복부 팽만의 정도를 정량적으로 평가하지 못한 점, MDCT 촬영 시 환자의 팔 위치와 호흡 상태가 실제 심정지 상황과 다를 수 있다는 점 등이 있습니다. 향후 다기관 연구를 통해 복부 팽만의 정도에 따른 적절한 가슴 압박 위치를 심층적으로 분석할 필요가 있습니다. 결론적으로, 복부 팽만이 있는 환자에서 LVMD 위치가 척추 몸통 높이의 절반 정도 위로 상승하는 것으로 확인되었습니다. 따라서 심정지 환자에서 가슴 압박 지점을 결정할 때 복부 팽만 유무를 고려해야 할 필요가 있습니다."
}