{
    "c_id": "32341_1",
    "domain": 2,
    "source": 1,
    "source_spec": "KJM",
    "creation_year": "2005",
    "content": "레닌-안지오텐신-알도스테론 시스템(RAAS)은 체액, 혈압, 심혈관계 조절에 중요한 역할을 합니다. 그러나 현대인에서는 RAAS의 과도한 활성화가 고혈압, 심혈관 질환, 당뇨병, 만성콩팥병 등의 주요 치료 목표가 되고 있습니다. 또한 비만, 과체중, 대사증후군도 RAAS를 자극하여 표적 장기 손상을 유발할 수 있습니다. 이를 억제하기 위해 안지오텐신 전환효소 억제제(ACEi), 안지오텐신 수용체 차단제(ARB), 알도스테론 수용체 길항제, 직접적 레닌 억제제 등이 사용됩니다. RAAS 억제제는 고혈압 및 표적 장기 보호를 위해 사용되지만, 고칼륨혈증의 위험이 있어 사용이 제한될 수 있습니다. 특히 신기능 저하, 심부전, 당뇨병 등의 기저 질환이 있는 환자에서 고칼륨혈증의 발생 가능성이 높아집니다. RAAS 억제제는 알도스테론 분비를 억제하거나 신혈류 감소 및 사구체여과율(GFR) 저하를 통해 칼륨 배설을 억제하여 고칼륨혈증을 유발할 수 있습니다. 신기능이 저하된 환자에서는 칼륨 배설이 주로 신장을 통해 이루어지기 때문에 고칼륨혈증이 흔히 발생합니다. 특히 말기신부전 환자에서는 고칼륨혈증의 위험이 매우 높습니다. 심부전 환자에서도 심박출량 감소, 저염식, RAAS 활성화 등이 고칼륨혈증의 위험을 증가시킵니다. 당뇨병 환자에서는 인슐린 결핍으로 인해 칼륨이 세포 내로 이동하지 못하고 혈청 칼륨이 상승할 수 있습니다. 또한 저레닌성 저알도스테론혈증이 동반될 경우 고칼륨혈증의 위험이 더욱 증가합니다. NSAIDs, 베타 차단제, 헤파린, 칼시뉴린 억제제 등도 고칼륨혈증을 유발할 수 있습니다. 특히 NSAIDs는 프로스타글란딘 합성을 억제하여 신혈류에 영향을 미치고, 저레닌성 저알도스테론혈증을 유발하여 고칼륨혈증과 대사성 산증을 초래할 수 있습니다. 항생제 중 trimethoprim-sulfamethoxazole은 나트륨 재흡수와 칼륨 배설을 억제하여 고칼륨혈증을 유발할 수 있습니다. 노인 인구에서는 신기능 저하, 다약제 복용, 퇴행성 질환 등으로 인해 고칼륨혈증의 위험이 증가합니다. 특히 만성콩팥병의 유병률이 높아 RAAS 억제제 사용 시 고칼륨혈증 발생 가능성이 더욱 높아질 수 있습니다. 고혈압 환자에서 RAAS 억제제 사용 시 고칼륨혈증의 발생 빈도는 낮으며, 혈청 칼륨 상승은 대개 임상적으로 큰 의미를 가지지 않습니다. 그러나 RAAS 억제제를 병용 투여할 경우 고칼륨혈증의 위험이 증가할 수 있습니다. 당뇨병 환자에서는 RAAS 억제제가 단백뇨 감소 및 신기능 보호 효과를 가지지만, 고칼륨혈증의 위험이 동반될 수 있습니다. 신기능이 저하된 환자에서도 RAAS 억제제 사용 시 고칼륨혈증의 발생 가능성이 있지만, 임상적으로 유의한 경우는 드뭅니다. RAAS 억제제 사용 시 고칼륨혈증을 예방하기 위해 환자의 기저 질환, 신기능 상태, 식이 상태 등을 평가하고, 필요 시 저칼륨 식이, 이뇨제 병용, 칼륨 결합 수지 사용 등을 고려해야 합니다. 약물 용량은 초기에는 저용량으로 시작하여 점진적으로 증량하며, 정기적인 전해질 및 신기능 검사를 통해 관리해야 합니다. RAAS 억제제 병용 투여 시에는 고칼륨혈증 발생 가능성을 염두에 두고 신중히 관리해야 합니다. 결론적으로, RAAS 억제제는 고혈압, 심혈관 질환, 당뇨병, 만성콩팥병 환자에서 유용하게 사용될 수 있으며, 고칼륨혈증의 위험은 낮은 편입니다. 그러나 정기적인 감시와 적절한 관리를 통해 고칼륨혈증을 예방하고 RAAS 억제제의 이점을 최대화하는 것이 중요합니다."
}