{
    "c_id": "33282_1",
    "domain": 2,
    "source": 1,
    "source_spec": "KJM",
    "creation_year": "2008",
    "content": "노인에게 적합한 운동 처방에 대해 다음과 같이 설명할 수 있습니다: 1. 근력 및 이동성 평가: 노인의 근력을 평가하기 위해 의자에서 일어서기, 계단 오르기, 스텝 테스트, 이동 및 활동 수준을 측정합니다. 2. 보행 평가: 보행 속도, 보폭, 이동 거리 등을 측정하여 보행 능력을 평가합니다. 3. 균형 평가: 동적 및 정적 균형, 자세 흔들림(postural sway)을 측정하여 균형 능력을 평가합니다. 4. 지구력 평가: 최대 산소 섭취량(VO2max), 심박수, 6분 걷기 테스트, 400m 걷기 테스트 등을 통해 지구력을 평가합니다. 5. 관절 가동 범위 평가: 관절의 움직임 범위를 측정하여 유연성을 평가합니다. 노화 과정에서 사람은 골격근 섬유의 30-40%를 잃게 되며, 특히 제2형 섬유(type II fibers)를 포함하는 근육(예: 외측광근, vastus lateralis muscle)에서 이러한 손실이 두드러집니다. (Learl, 1995) 노인의 최대 사지 속도는 비교적 낮은 외부 저항(예: 1RM의 40%)에서 차이를 보이며, 이는 노인의 보행 속도와 밀접한 연관이 있습니다. 지역사회에 거주하는 노인 여성들을 대상으로 한 연구에서는 파워 중심의 운동 중재가 효과적임이 밝혀졌습니다. (Pieking, Aging Res, 2000)"
}