{
    "c_id": "35127_1",
    "domain": 2,
    "source": 1,
    "source_spec": "KSEM",
    "creation_year": "2010",
    "content": "1. 일시적인 의식소실은 응급실에서 흔히 볼 수 있는 증상으로, 응급실 내원 환자의 약 3%, 입원 환자의 약 6%가 이 증상을 주소로 내원합니다. 2. 의식소실 환자의 정확한 진단과 치료 방향을 결정하는 것은 어려운 일입니다. 이는 환자가 의식소실 당시의 상황을 기억하지 못하거나, 보호자가 현장에 없어서 경련 여부나 의식소실 후 깨어난 상황에 대한 정보를 제공하지 못하는 경우가 많기 때문입니다. 3. 응급실에서는 24시간 심전도 검사, 기립경사검사, 뇌파검사 등의 사용이 제한적이기 때문에, 경련성 질환과 실신을 감별하는 데 어려움이 있습니다. 4. 기존 연구에서는 혈중 크레아틴 인산활성효소(CPK) 수치, 혈중 암모니아, 젖산 수치 등을 이용해 감별하려는 시도가 있었으나, 응급실 내원 당시의 수치만으로는 의미 있는 결론에 도달하지 못했습니다. 5. 본 연구는 응급실 내원 당시의 혈청검사와 동맥혈 가스분석검사가 전신성 경련과 실신을 감별하는 데 유용한 정보를 제공할 수 있는지 확인하기 위해 진행되었습니다. 6. 연구 대상은 2009년 1월부터 12월까지 12개월간 일개 권역 응급의료센터에 내원한 18세 이상의 일시적 의식소실 환자 중 증상 발생 4시간 이내에 내원한 환자들로, 경련군 75명과 실신군 78명이 포함되었습니다. 7. 연구 결과, 경련군에서 수축기 혈압, 이완기 혈압, 평균 혈압, 심박수가 실신군보다 유의하게 높았습니다. 8. 혈청검사 결과, 경련군에서 LDH와 암모니아 수치가 유의하게 높았고, tCO2는 낮게 측정되었습니다. 9. 동맥혈 가스분석검사 결과, 경련군에서 pH와 중탄산염 농도가 낮았으며, 젖산 수치는 높게 측정되었습니다. 10. ROC 곡선 분석 결과, 혈청 tCO2, 암모니아, 동맥혈 pH, 중탄산염, 젖산이 경련과 실신을 감별하는 데 유용한 지표로 확인되었습니다. 11. 특히, 의식소실 후 응급실 내원 시간이 짧을수록 암모니아와 젖산의 AUC 값이 증가하여 감별 진단에 더 유용한 것으로 나타났습니다. 12. 다변량 로지스틱 회귀분석 결과, 동맥혈 pH 감소와 혈중 암모니아 상승이 독립적인 예측인자로 확인되었습니다. 13. 경련 후 응급실 방문 시간이 짧을수록 혈중 암모니아 수치가 감별 진단에 더 유용한 것으로 나타났습니다. 14. 동맥혈 가스분석검사를 시행하지 않은 경우, 혈청 tCO2를 이용하는 것이 도움이 될 수 있습니다. 15. 본 연구는 후향적 단일 센터 연구로 제한점이 있으며, 향후 다양한 병원에서 전향적 연구가 필요합니다. 16. 결론적으로, 증상 발생 후 4시간 이내에 응급실에 내원한 일시적 의식소실 환자에서 혈청 암모니아 수치와 동맥혈 pH가 전신성 경련과 실신을 감별하는 데 유용한 지표로 확인되었습니다. 17. 추후 대규모 전향적 연구를 통해 본 연구 결과를 보완하고 확장할 필요가 있습니다."
}