{
    "c_id": "32938_1",
    "domain": 2,
    "source": 1,
    "source_spec": "KJM",
    "creation_year": "2006",
    "content": "프로톤펌프억제제(PPI)는 위산 분비를 억제하는 데 매우 효과적인 약물로, 위식도 역류 질환과 소화성 궤양 치료에 널리 사용되고 있습니다. 그러나 PPI의 장기 복용은 위산 분비 감소로 인해 위 점막에 여러 부작용을 초래할 수 있습니다. 대표적인 부작용으로는 위산 분비세포 증식, 분비선 낭종, 고가스트린혈증, 위저선 용종 등이 있습니다. 특히, PPI의 장기 복용이 위축성 위염과 위암의 발생에 영향을 미칠 수 있다는 보고가 있습니다. PPI는 위 벽세포의 수소/칼륨 교환 ATP효소를 비가역적으로 차단하여 위산 분비를 약 99%까지 억제합니다. 이러한 작용은 위식도 역류 질환과 소화성 궤양 치료에 효과적이지만, 장기 복용 시 만성적인 위산 저하증, 고가스트린혈증, 위 점막 위축 등의 부작용을 유발할 수 있습니다. PPI의 장기 복용과 Helicobacter pylori(H. pylori) 감염은 위축성 위염 및 위암 발생에 중요한 역할을 합니다. H. pylori 감염 초기에는 전정부 점막에 집락화하여 전정부 위염을 유발하지만, 만성 감염 시 체부로 이주하여 체부 위염을 유발하고 위산 분비를 억제합니다. 이러한 과정은 위축성 위염으로 진행될 수 있으며, 이는 십이지장 궤양, 위궤양, 위암 발생과 관련이 있습니다. 특히, H. pylori 감염 환자에서 PPI를 장기 복용하면 위축성 위염의 발생 위험이 증가할 수 있습니다. PPI의 장기 복용은 위 카르시노이드 종양 발생과도 연관이 있습니다. PPI 복용으로 인해 고가스트린혈증이 발생하고, 이는 장크롬 친화성 세포(ECL 세포)의 증식을 유발하여 위 카르시노이드 종양을 초래할 수 있습니다. 그러나 이러한 종양은 대체로 비침습적이며, 명확한 인과관계는 아직 밝혀지지 않았습니다. 또한, PPI 복용으로 인한 체부 위축성 위염은 위 선암 발생의 위험인자로 알려져 있습니다. 동물실험에서는 PPI 복용이 위축성 위염의 진행을 가속화하고 위 선암 발생을 증가시키는 것으로 나타났습니다. 특히, CagA 양성 H. pylori 감염 시 위 선암 발생 위험이 더 높아지는 것으로 보고되었습니다. 따라서 PPI를 장기 복용해야 하는 경우, H. pylori 감염 여부를 확인하고 감염이 확인되면 제균요법을 병행하는 것이 중요합니다. 이를 통해 위축성 위염과 위암 발생 위험을 줄일 수 있습니다. 또한, PPI 복용 시 적정 용량과 기간을 설정하여 부작용을 최소화해야 합니다."
}