{
    "c_id": "1293_47",
    "domain": 2,
    "source": 1,
    "source_spec": "guide_kr",
    "creation_year": "2023",
    "content": "1. 클레마스틴(Clemastine)은 항히스타민제로, 알레르기 증상 완화에 사용되며 관련 연구는 94건이 보고되었습니다. 2. 사이프로헵타딘(Cyproheptadine)은 항히스타민 및 항세로토닌 작용을 가지며, 관련 연구는 639건이 있습니다. 3. 디메틴덴(Dimethindene)은 항히스타민제로, 관련 연구는 46건이 보고되었습니다. 4. 디펜히드라민(Diphenhydramine)은 1세대 항히스타민제로, 진정 작용이 있으며 관련 연구는 574건이 있습니다. 5. 독실아민(Doxylamine)은 수면 보조제로도 사용되는 항히스타민제로, 관련 연구는 41건이 보고되었습니다. 6. 하이드록시진(Hydroxyzine)은 항히스타민 및 항불안제로 사용되며, 관련 연구는 786건이 있습니다. 7. 케토티펜(Ketotifen)은 비만세포 안정화 및 항히스타민 작용을 가지며, 관련 연구는 222건이 보고되었습니다. 8. 로라타딘(Loratadine)은 2세대 항히스타민제로, 졸림이 적고 관련 연구는 472건이 있습니다. 9. 메타피릴렌(Methapyrilene)은 항히스타민제로, 관련 연구는 3건이 보고되었습니다. 10. 올로파타딘 하이드로클로라이드(Olopatadine Hydrochloride)는 항히스타민 및 항염증 작용을 가지며, 관련 연구는 125건이 있습니다. 11. 페니라민(Pheniramine)은 항히스타민제로, 관련 연구는 406건이 보고되었습니다. 12. 프로메타진(Promethazine)은 항히스타민 및 항구토제로 사용되며, 관련 연구는 392건이 있습니다. 13. 피리라민(Pyrilamine)은 항히스타민제로, 관련 연구는 19건이 보고되었습니다. 14. 트리펠레나민(Tripelennamine)은 항히스타민제로, 관련 연구는 7건이 있습니다. 15. 트리프롤리딘(Triprolidine)은 항히스타민제로, 관련 연구는 72건이 보고되었습니다. 16. 트리암시놀론(Triamcinolone)은 코르티코스테로이드로, 염증 완화에 사용되며 관련 연구는 1355건이 있습니다. 17. 모메타손 푸로에이트(Mometasone Furoate)는 코르티코스테로이드로, 알레르기 비염 치료에 사용되며 관련 연구는 395건이 보고되었습니다. 18. 글루코코르티코이드(Glucocorticoids)는 염증 및 면역 반응 조절에 사용되며, 관련 연구는 4445건이 있습니다. 19. 부신피질 호르몬(Adrenal Cortex Hormones)은 다양한 염증성 질환 치료에 사용되며, 관련 연구는 14135건이 보고되었습니다. 20. 베클로메타손(Beclomethasone)은 코르티코스테로이드로, 관련 연구는 1121건이 있습니다. 21. 류코트리엔 길항제(Leukotriene Antagonists)는 염증 매개체를 억제하며, 관련 연구는 435건이 보고되었습니다. 22. 플루티카손(Fluticasone)은 코르티코스테로이드로, 관련 연구는 1753건이 있습니다. 23. 플루오시논라이드(Fluocinonide)는 강력한 코르티코스테로이드로, 관련 연구는 51건이 보고되었습니다. 24. 부데소나이드(Budesonide)는 코르티코스테로이드로, 관련 연구는 1818건이 있습니다. 25. 류코트리엔 수용체 길항제(Leukotriene Receptor Antagonists)는 알레르기 및 천식 치료에 사용되며, 관련 연구는 4272건이 보고되었습니다. 26. 몬테루카스트(Montelukast)와 같은 류코트리엔 길항제는 알레르기 비염 및 천식 치료에 사용되며, 관련 연구는 2316건이 보고되었습니다."
}