{
    "c_id": "35441_1",
    "domain": 2,
    "source": 1,
    "source_spec": "KSEM",
    "creation_year": "2013",
    "content": "초오(aconitum species)는 전통적으로 관절통, 급성 복통, 신경계 질환 등의 치료에 민간요법으로 사용되어 왔으나, 그 뿌리와 줄기에는 맹독성 알칼로이드(aconitine)가 포함되어 있어 과다 복용 시 심혈관계에 심각한 독작용을 일으킬 수 있습니다. 이러한 독작용은 심실기외수축, 심실빈맥, 결합 이소성 박동, 각차단, 심실세동 등 다양한 심부정맥을 유발하며, 심한 경우 사망에 이를 수 있습니다. Aconitine은 나트륨 통로 수용체에 작용하여 세포 내 나트륨 유입을 증가시키고, 이로 인해 심근세포의 나트륨 및 칼슘 이온의 항상성이 깨지며 탈분극이 지속됩니다. 이로 인해 재분극이 지연되고, 심근세포의 활동전위가 증가하며, 심전도에서 QT 간격이 연장됩니다. QT 간격의 연장은 심각한 심실성 부정맥과 연관이 있으며, 이는 심혈관계 질환의 이환율 및 사망률 증가와도 관련이 있습니다. 이번 연구는 초오 중독 환자에서 QTc 간격 연장과 부정맥 발생 간의 관계를 분석하고, QTc 간격 연장이 부정맥 발생의 예측 인자로서의 의의를 가지는지 확인하기 위해 진행되었습니다. 연구 대상은 2002년부터 2013년까지 초오 중독으로 계명대학교 동산의료원 응급의료센터에 내원한 환자 41명이었으며, QTc 간격 연장 유무에 따라 두 군으로 나누어 분석하였습니다. 연구 결과, QTc 간격이 연장된 환자군에서 부정맥 발생 빈도가 유의하게 높았으며, 특히 심실 조기 박동과 각차단이 빈번하게 관찰되었습니다. QTc 간격 연장은 심실 조기 박동 발생과 밀접한 연관이 있었으며, 연장 QTc군에서 심실 조기 박동이 94%의 빈도로 나타났습니다. 또한, 각차단은 연장 QTc군에서만 발생하였으며, 우각차단이 가장 흔했습니다. QTc 간격 연장은 부정맥 발생뿐만 아니라 저혈압 발생과도 연관이 있었으며, 연장 QTc군에서 재원 기간이 더 길었습니다. 초오를 생으로 섭취한 경우 QTc 간격 연장이 더 빈번하게 나타났으며, 이는 초오를 끓여 섭취할 경우 aconitine이 가수분해되어 독성이 감소하기 때문으로 추정됩니다. Aconitine은 심장 세포막의 나트륨 통로를 활성화 상태로 유지하여 나트륨 이온의 유입을 증가시키고, 이로 인해 칼슘 이온의 유입이 가속화되며 활동전위가 연장됩니다. 이러한 기전은 QTc 간격 연장과 부정맥 발생의 주요 원인으로 작용합니다. 이번 연구는 초오 중독 환자에서 QTc 간격 연장이 부정맥 발생의 예측 인자로 활용될 수 있음을 보여주었으며, QTc 간격 연장 여부를 통해 환자의 임상 경과를 예측하고 적절한 치료를 계획하는 데 기여할 수 있을 것으로 보입니다. 앞으로 초오 중독 환자에서 QTc 간격의 변화 추이와 부정맥 발생 간의 관계를 분석하는 추가 연구가 필요합니다."
}