{
    "c_id": "1488_3",
    "domain": 2,
    "source": 1,
    "source_spec": "guide_kr",
    "creation_year": "null",
    "content": "1. 임종기 환자의 섬망 치료는 환자의 현재 임상 상태와 예후뿐만 아니라 돌봄의 목적, 영적, 심리적, 사회적 요인을 종합적으로 고려해야 합니다. 약물 처방 전에 가능한 모든 비약물적 중재를 우선적으로 시행해야 합니다. 2. 섬망 예방 및 치료를 위해 다학제적 접근이 효과적일 수 있습니다. 예를 들어, 신체 억제를 피하고 다학제적 중재 프로그램을 적용한 연구에서는 섬망 발생 및 악화 빈도가 유의미하게 감소한 반면, 다른 연구에서는 일반 치료와 비교해 유의미한 차이를 보이지 않았습니다. 이는 임종기 환자에게도 적용 가능하다는 합의가 있었습니다. 3. 캐나다 노인 정신의학회는 신체 억제대 사용이 섬망 발생 위험을 증가시킬 수 있으므로 임종기 섬망 환자에게 억제대를 사용하지 말 것을 권고합니다. 다만, 신체적 상해 위험이 있거나 다른 방법이 효과가 없을 때, 그리고 신체 억제의 이득이 위험을 초과할 때에만 제한적으로 사용할 수 있습니다. 4. 섬망 환자에게는 유치 도뇨관 및 정맥 주사 사용을 최소화하고, 치료 방향을 재설명하거나 정신신경약물 투약 필요성을 재평가하며, 안전사고 예방 활동을 시행해야 합니다. 5. 섬망 환자의 비약물적 중재는 효과가 일관되지 않을 수 있으나, 임종기 환자에게는 절대적 효과 크기를 고려하여 진료 현장에서 활용도가 높다고 판단되어 권고 등급이 상향 조정되었습니다. 6. 임종기 섬망 환자에게 약물 치료를 고려하기 전, 약물 중재의 목표를 명확히 해야 합니다. 약물 선택 시 표적 증상, 조절 목표, 부작용 등을 고려하여 비전형 항정신병 약물(리스페리돈, 올란자핀, 쿠에티아핀 등)을 선택할 수 있습니다. 7. 할로페리돌 사용 시 QT 간격 연장 위험이 증가할 수 있으므로 주의가 필요하며, 초조가 심한 환자에게는 고용량이 필요할 수 있습니다. 파킨슨병이나 루이체 치매가 동반된 환자에게는 비전형 항정신병 약물이 권고됩니다. 8. 항정신병 약물은 간질 발작 역치를 낮출 수 있으므로 대뇌 전이 환자 등 위험군에서는 주의가 필요합니다. 약물 사용 시 단일 제제, 최소 용량을 목표로 하며, 정기적 용량이나 증상에 따른 추가 투약은 신중히 결정해야 합니다. 9. 벤조디아제핀은 섬망 환자에서 역설적 흥분을 일으키거나 섬망을 악화시킬 수 있으므로 사용을 피해야 합니다. 다만, 금단 증상으로 인한 섬망 발생 시에는 약물 재도입을 고려할 수 있습니다. 10. 조절되지 않는 섬망의 경우, 호스피스 완화의료 전문가나 정신건강의학과와 협의하거나 완화적 진정을 고려할 수 있습니다. 11. 임종기 환자의 불안 및 초조를 평가하고, 원인 및 가역적 요인을 파악하여 비약물적 및 약물적 중재를 시행해야 합니다. 불필요한 약물 사용이나 모니터링 장비 연결을 중단하고, 통증 등 증상을 적극적으로 해결해야 합니다. 12. 환자와 가족의 심리적, 영적 지지를 위해 의료진은 신체적, 정신적, 사회적, 영적 상태를 포괄적으로 평가해야 합니다. 환자와 가족의 가치, 의미, 종교적 세계관 등을 확인하며, 상실감, 애도, 비탄 등을 점차적으로 파악해야 합니다. 13. 환자와 가족의 영적 돌봄을 위해 반복적이고 체계적인 의사소통이 필요합니다. 환자의 감정을 공감하며, 적절한 언어적, 비언어적 방법을 통해 지지를 제공해야 합니다. 14. 임종기 환자와 가족의 의사결정 과정에서 환자의 가치와 선호를 반영한 치료 목표를 설정해야 합니다. 환자와 가족이 버려졌다는 느낌을 받지 않도록 돌봄의 연속성을 유지해야 합니다. 15. 가족 회의를 통해 환자의 상태, 질병 과정, 치료 옵션 등을 논의하고, 돌봄 목표와 계획을 수립할 수 있습니다. 이를 통해 가족과 의료진 간의 신뢰와 지원 체계를 강화할 수 있습니다. 16. 임종기 환자와 가족의 요구를 정기적으로 확인하고 이를 문서화하여 의료진 간에 공유해야 합니다. 이를 통해 환자와 가족이 더 나은 돌봄을 받았다고 느낄 수 있습니다. 17. 임종기 환자의 가족 돌봄을 위해 포괄적이고 전인적인 평가를 고려해야 합니다. 가족의 감정, 약점, 사회적 지지 체계 등을 평가하고, 이를 바탕으로 적절한 지원을 제공해야 합니다."
}