{
    "c_id": "1467_2",
    "domain": 2,
    "source": 1,
    "source_spec": "guide_kr",
    "creation_year": "null",
    "content": "수술 부위 감염 예방을 위한 항생제 투여 시점에 대한 권고 사항은 다음과 같습니다: 1. 항생제 투여 시점: 수술 예방적 항생제는 피부 절개 전 120분 이내에 투여하는 것이 권장됩니다. 특히, 반감기가 짧은 항생제의 경우 피부 절개에 가까운 시점(60분 이내)에 투여하는 것이 더 효과적일 수 있습니다. 2. 항생제 반감기 고려: 반감기가 짧은 항생제는 너무 일찍 투여될 경우, 피부 절개 시점 및 수술 중 항생제의 혈청 및 조직 농도가 충분하지 않을 수 있습니다. 따라서 항생제의 반감기를 고려하여 투여 시점을 결정해야 합니다. 3. 투여 시점에 따른 효과: 피부 절개 전 60분 이내에 투여한 경우와 60~120분 사이에 투여한 경우, 수술 부위 감염률 감소에 있어 유의미한 차이는 없었습니다. 그러나 반감기가 짧은 항생제는 피부 절개에 더 가까운 시점에 투여하는 것이 적절할 수 있습니다. 4. 국내 권고 사항: 국내에서는 대부분 반감기가 짧은 항생제를 사용하며, 항생제 투여 시점은 피부 절개 전 1시간 이내로 권고되고 있습니다. 5. 항생제 종류와 투여 시간: 반감기가 긴 항생제(vancomycin, fluoroquinolones 등)는 120분 이내 투여가 가능하며, 반감기가 짧은 항생제(cefazolin 등)는 60분 이내 투여가 권장됩니다. 6. 수술 환경에 따른 조정: 병실에서 항생제를 투여해야 하는 경우, 피부 절개 전 120분 이내 투여를 기준으로 삼을 수 있습니다. 수술실에서 투여가 가능한 경우, 피부 절개 전 60분 이내 투여가 적절합니다. 7. 지속적인 감시 필요성: 적절한 항생제 투여 시점을 체계적으로 감시하고, 이를 벗어난 경우 원인을 파악하여 수정하는 과정이 필요합니다. 이를 위해 병원 내 감시 체계를 마련하고, 전산화된 의료 시스템을 활용하는 것이 중요합니다. 8. 권고 사항의 근거: 메타 분석 결과, 120분 이내 항생제 투여가 수술 부위 감염을 줄이는 데 효과적임이 확인되었습니다. 그러나 60분 이내 투여가 60~120분 사이 투여보다 우월하다는 근거는 부족합니다. 9. 추가 연구 필요성: 항생제의 반감기와 투여 시점에 따른 효과를 구체적으로 분석한 연구가 부족하므로, 임상의는 수술 전후 적절한 혈청 및 조직 농도를 보장하기 위해 항생제의 반감기를 고려해야 합니다. 10. 국내 평가 기준: 건강보험심사평가원에서는 수술 예방적 항생제 사용 평가를 통해 피부 절개 전 1시간 이내 항생제 투여를 권고하고 있으며, 이는 수술 부위 감염 위험을 줄이는 데 기여할 것으로 보입니다. 11. 권고 사항의 최종 결정: 120분 이내 항생제 투여를 권고하며, 60분 이내 투여가 더 우월하다는 근거는 부족하므로, 120분 이내 투여를 최종 권고로 결정하였습니다."
}