{
    "c_id": "3738_1",
    "domain": 2,
    "source": 1,
    "source_spec": "KJG",
    "creation_year": "2005",
    "content": "대장암은 소화기계 악성 종양 중 가장 흔한 질환으로, 서구에서는 주로 70대에서 발생 빈도가 높습니다. 최근 우리나라에서도 급격한 노인 인구 증가로 인해 대장암 발생 빈도가 더욱 증가할 것으로 예상됩니다. 노인 인구의 증가는 심혈관 및 뇌혈관 질환의 발생 증가와 연관되며, 이에 따라 항혈소판제인 아스피린과 항응고제인 와파린의 사용이 대표적으로 증가하고 있습니다. 아스피린은 아라키돈산을 트롬복산 A2로 전환시키는 COX-1 효소를 억제하여 항혈소판 작용을 나타냅니다. 와파린은 비타민 K 의존 혈액 응고 인자(factor II, VII, IX, X)와 단백질 C, S의 생성을 차단하여 혈액 응고를 방지합니다. 이들 약물은 출혈 경향을 증가시키며, 특히 아스피린은 위장 점막 보호에 필수적인 프로스타글란딘 생성을 저하시켜 소화성 궤양, 출혈, 천공 등의 부작용을 초래할 수 있습니다. 와파린은 아스피린보다 출혈 경향이 더 강력하므로, 이를 방지하기 위해 프로트롬빈 시간을 주기적으로 측정해야 합니다. 와파린 복용 중 하부 위장관 출혈로 내원한 환자에서 조기에 대장암을 진단할 수 있다는 보고가 있지만, 이러한 출혈 경향을 나타내는 약물에 의한 하부 위장관 출혈이 대장암의 조기 진단 단서로 작용할 수 있는지에 대한 연구는 아직 미미한 실정입니다. 이에 저자는 아스피린과 와파린 복용 중 나타나는 여러 증상이 대장암의 조기 진단 단서로 작용할 수 있는지 알아보고자 하였으며, 더불어 최근 아스피린과 같은 비스테로이드 항염제가 COX-2 효소를 차단하여 소화기계 종양, 특히 대장암 및 대장 용종의 위험성을 감소시킨다는 점에 주목하여, 아스피린 복용 대장암 환자에서 아스피린이 대장암 및 동시 용종에 미치는 영향을 조사하였습니다. 1999년 1월부터 2003년 12월까지 연세대학교 세브란스병원에서 대장암으로 진단받은 환자 중 아스피린 또는 와파린을 복용한 환자를 증례군으로, 이러한 약물을 복용하지 않은 환자를 대조군으로 설정하였습니다. 아스피린 복용군은 대장암 진단 전 최소 1년 이상 복용한 환자를, 와파린 복용군은 진단 전 최소 6개월 이상 복용한 환자를 대상으로 하였습니다. 대조군은 증례군과 성별, 나이가 일치하며, 증례군의 대장암 진단일로부터 1년 이내에 진단받은 환자 중 가장 가까운 시기에 진단받은 환자를 3배수로 선정하였습니다. 연구 결과, 아스피린 복용군에서는 대장암의 장관 내 원주상 비율이 낮고, 동시 용종의 비율과 평균 개수가 적은 것으로 나타났습니다. 이는 아스피린의 항대장암 및 항용종 효과와 관련이 있을 수 있습니다. 와파린 복용군에서는 대조군에 비해 Duke 병기 D가 유의하게 적었으며, 이는 와파린의 항전이 효과와 관련이 있을 것으로 추정됩니다. 그러나 아스피린과 와파린 복용 중 출혈 증상이 대장암의 조기 진단 단서로 작용하지는 않았습니다. 아스피린의 항대장암 및 항용종 효과는 COX-2 효소 억제와 관련된 세포 사멸 및 혈관 신생 억제와 연관이 있습니다. 아스피린 복용 기간과 용량에 따라 효과가 달라질 수 있으며, 저용량 아스피린(100mg) 복용 시에도 용종 억제 효과가 관찰되었습니다. 그러나 항대장암 및 항용종 효과를 나타내기 위한 아스피린의 최적 용량과 복용 기간에 대해서는 추가적인 연구가 필요합니다. 결론적으로, 대장암으로 진단받은 환자 중 아스피린 또는 와파린을 복용 중인 환자에서 출혈 등의 증상이 흔히 나타났으나, 이러한 증상이 질병의 조기 진단 단서로 작용하지는 않았습니다. 와파린 복용군에서 관찰된 항전이 효과와 아스피린 복용군에서 나타난 항대장암 및 항용종 효과는 추가적인 연구를 통해 더 명확히 규명되어야 할 것입니다."
}