{
    "c_id": "35786_1",
    "domain": 2,
    "source": 1,
    "source_spec": "KSEM",
    "creation_year": "2018",
    "content": "1. 현대 사회에서 중증 외상의 발생 빈도는 기술과 과학의 발전, 교통사고, 상해 및 재해의 증가로 인해 증가하고 있으며, 특히 활동이 많은 젊은 연령층에서 높은 빈도를 보입니다. 이는 개인뿐만 아니라 가정, 지역사회, 국가적으로도 큰 손실을 초래합니다. 2. 대부분의 선진국에서는 1960년대 이후 국가적 차원에서 외상환자를 위한 체계적인 전달 시스템을 구축하여 병원 전 단계에서부터 외상환자의 분류 및 이송을 시행하고 있습니다. 현재는 헬리콥터와 같은 항공 이송 수단도 활용되고 있습니다. 3. 외상환자의 치료는 자원과 인력이 많이 필요한 집중적인 과정이며, 외상센터는 치료 가능한 환자 수와 보유 장비, 병원의 규모에 따라 분류됩니다. 그러나 인력, 자원, 지리적 한계로 인해 모든 외상환자를 외상센터에서 치료하기는 어렵습니다. 4. 많은 외상환자는 비외상센터에서 초기 치료를 받거나 안정화된 후 외상센터로 전원됩니다. 하지만 외상센터로 직접 이송된 환자와 비외상센터에서 전원된 환자의 예후에 대한 연구는 다양하게 진행되었으나, 전원이 예후에 미치는 영향에 대한 명확한 결론은 아직 내려지지 않았습니다. 5. 우리나라에서는 2008년부터 권역별 전문질환센터 설립 사업을 통해 전국적으로 권역외상센터가 운영되고 있습니다. 그러나 국내에서는 비외상센터에서 전원된 환자와 외상센터로 직접 내원한 환자의 예후를 비교한 연구가 거의 없습니다. 6. 본 연구는 부산의 한 권역외상센터를 중심으로 비외상센터에서 전원된 환자군과 외상센터로 직접 내원한 환자군의 예후를 비교하고, 전원이 예후에 미치는 영향을 분석하기 위해 후향적 단면 연구로 설계되었습니다. 7. 연구 대상은 2015년 12월부터 2016년 9월까지 외상센터에 내원한 중증 외상환자 중 ISS(Injury Severity Score)가 15점 이상인 18세 이상의 성인으로 설정되었습니다. 외상센터 도착 시 또는 응급실 내에서 사망한 환자와 외상센터 응급실에서 전원된 환자는 연구에서 제외되었습니다. 8. 연구 결과, 외상센터로 직접 내원한 환자군과 비외상센터에서 전원된 환자군 간의 48시간, 7일, 입원 중 사망률에는 통계적으로 유의한 차이가 없었습니다. 또한 중환자실 입원 기간과 총 입원 기간에도 두 군 간의 차이는 없었습니다. 9. 전원군의 경우 외상센터까지 도달하는 데 걸린 시간과 최종 치료 시간은 직접 내원군에 비해 더 길었으나, 사망률과 입원 기간에는 큰 영향을 미치지 않았습니다. 10. 전원군의 예후에 영향을 미치는 요인을 분석한 결과, 비외상센터에서 시행된 기도 삽관, 수혈, 중심정맥관 삽입, 승압제 투여 등의 처치는 사망 확률을 높이는 요인으로 나타났습니다. 이는 해당 처치가 중증도가 높은 환자에게 주로 시행되었기 때문으로 해석됩니다. 11. 비외상센터에서의 초기 치료가 미숙하지 않음을 간접적으로 보여주는 결과로, 가까운 비외상센터에서 환자를 안정화한 후 외상센터로 전원하는 것이 일부 환자에게는 더 유리할 수 있음을 시사합니다. 12. 두부 손상의 경우, 비외상센터에서 안정화 치료를 하지 않고 바로 수술이 가능한 외상센터로 이송하는 것이 환자의 예후에 더 유리하다는 연구 결과도 있습니다. 이는 두부 손상의 높은 사망률과 관련이 있습니다. 13. 본 연구는 단일 외상센터에서 시행된 후향적 연구로, 지역적 한계와 의무기록의 누락 가능성이 제한점으로 지적됩니다. 또한, 퇴원 후 환자의 장애율이나 삶의 질에 대한 분석은 포함되지 않았습니다. 14. 외상센터로 직접 내원한 환자와 비외상센터에서 전원된 환자 간의 예후 차이는 없었으며, 이는 비외상센터에서의 초기 치료가 적절히 이루어졌음을 보여줍니다. 다만, 외상센터로의 직접 이송이 필요한 경우도 존재하며, 특히 두부 손상과 같은 중증 외상에서는 신속한 이송이 중요합니다."
}