{
    "c_id": "1471_3",
    "domain": 2,
    "source": 1,
    "source_spec": "guide_kr",
    "creation_year": "2023",
    "content": "괄약근 손상이 있는 대변실금 환자에서 괄약근 성형술은 장기적으로 증상 개선에 효과적이며, 환자의 삶의 질을 향상시키는 데 기여할 수 있습니다. 연구에 따르면, 수술 후 평균 90개월의 추적 관찰 결과, 대변실금 증상이 일관되게 개선되었으며, 환자 만족도가 높았습니다. 그러나 대조군이 없는 연구 설계로 인해 자연 치유와의 구분이 어려운 점, 연구의 비뚤림 위험 및 정밀성 부족 등으로 근거 수준은 매우 낮음으로 평가되었습니다. 괄약근 성형술의 부작용으로는 수술 부위 감염(13%), 요로 감염 및 배뇨 장애(8.3%), 통증 및 불편감(15%), 항문 협착(8.3%) 등이 보고되었습니다. 수술 결과는 집도의의 숙련도와 괄약근 손상의 정도에 따라 달라질 수 있습니다. 괄약근 손상이 명확한 대변실금 환자에서 괄약근 성형술은 보존적 치료에 반응하지 않을 경우 권고됩니다. 천수신경자극술(SNS)은 보존적 치료에 반응하지 않는 대변실금 환자에서 효과적인 대안으로 제시됩니다. 시험적 자극을 통해 치료 반응을 확인한 후 영구적 자극기를 삽입하며, 증상 개선과 삶의 질 향상이 보고되었습니다. 그러나 합병증으로 감염, 기기 오작동, 통증 등이 발생할 수 있으며, 자기공명영상(MRI) 제한 등의 단점이 있습니다. SNS는 비교적 덜 침습적이며, 치료 반응을 선별할 수 있는 장점이 있으나, 비용과 의료진의 경험 부족이 장애 요인으로 작용할 수 있습니다. 장루조성술은 다른 치료에 효과가 없는 대변실금 환자에서 삶의 질을 개선하는 데 효과적일 수 있습니다. 연구에 따르면, 장루조성술 후 삶의 질 제한이 72% 감소하였으며, 사회적 제약도 줄어들었습니다. 그러나 장루 탈출증(6%), 장루 주위 탈장(13%), 피부 합병증(13%) 등의 부작용이 보고되었으며, 장루 관리에 대한 부담과 경제적 비용이 주요 장애 요인으로 작용합니다. 장루조성술은 최후의 치료 옵션으로 고려되며, 환자에게 충분한 정보 제공과 상담이 필요합니다. 결론적으로, 괄약근 성형술, 천수신경자극술, 장루조성술은 각각의 적응증과 환자 상태에 따라 선택적으로 사용될 수 있으며, 치료 전 환자와의 충분한 논의와 정보 제공이 중요합니다."
}