{
    "c_id": "35852_1",
    "domain": 2,
    "source": 1,
    "source_spec": "KSEM",
    "creation_year": "2019",
    "content": "1. 자살 시도는 심리적 고통, 경제적 문제, 신체적 건강, 사회적 요인, 개인적 성격 등 다양한 요인들이 상호작용하여 발생하는 복합적인 현상입니다. 2. OECD 국가들의 자살률은 지난 20여 년간 완만하게 감소하고 있으나, 한국은 예외적으로 자살률이 급격히 증가하고 있습니다. 3. 자살로 인한 사회적 비용은 약 6조 5천억 원으로 추정되며, 이를 해결하기 위한 국가적 차원의 노력이 진행되고 있습니다. 4. 치명적인 수단(목매기, 추락, 가스 중독, 농약 음독 등)을 사용한 자살 시도는 사망률이 매우 높으며, 이러한 환자들에 대한 이해는 자살 예방 정책 수립에 중요한 역할을 합니다. 5. 본 연구는 2006년부터 2015년까지의 퇴원 손상 심층 조사 데이터를 활용하여 고의적 자해로 입원한 환자들의 위험 요인과 특성을 분석하였습니다. 6. 자해 수단은 치명도에 따라 치명적(목매기, 농약 음독 등)과 비치명적(약물 음독, 자상 등)으로 분류되었으며, 사망률을 기준으로 치명도를 구분하였습니다. 7. 연구 결과, 치명적인 자해 수단을 선택한 환자들은 남성, 고령(50대 이상), 농촌 거주, 동반 질환 과거력이 있는 경우가 많았습니다. 8. 반면, 비치명적인 자해 수단을 선택한 환자들은 여성, 젊은 연령(35세 이하), 정신 질환 과거력이 있는 경우가 많았습니다. 9. 자살 시도자들의 위험 요인으로는 정신적 문제, 가족 갈등, 경제적 문제 등이 주요하게 나타났습니다. 10. 잠재 계층 분석(LCA)을 통해 자살 시도자들을 네 개의 계층으로 분류하였으며, 각 계층은 성별, 연령, 위험 요인 등에 따라 특성이 달랐습니다. 11. 치명적인 자해 수단을 선택한 계층은 주로 남성, 고령층, 농촌 거주자들이었으며, 비치명적인 수단을 선택한 계층은 주로 여성, 젊은 연령층이었습니다. 12. 자살 예방을 위해서는 자살 시도자들의 위험 요인과 치명적인 자살 수단의 선택 요인을 이해하고, 이를 기반으로 맞춤형 예방 전략을 수립해야 합니다. 13. 자살 수단의 접근을 제한하는 것은 자살 예방에 효과적인 전략으로, 각국의 문화와 정책에 따라 자살 수단의 선택이 다르게 나타납니다. 14. 한국에서는 가스 중독이 주요 자살 수단으로 나타나며, 살충제와 같은 치명적인 수단의 접근을 제한하는 정책이 필요합니다. 15. 자살 시도자들의 정신 질환 유병률과 재시도 위험이 높기 때문에, 입원 기간 동안 치료적 환경을 제공하고, 경제적 문제와 동반 질환을 지원할 수 있는 제도적 뒷받침이 필요합니다. 16. 의료기관에서는 자살 예방 역량 강화를 위한 보건의료인의 교육이 필요하며, 이를 위해 자살 시도자들의 특성을 파악하고 예방 활동에 반영해야 합니다. 17. 본 연구는 자살 시도자들의 특성과 유형을 분석하여 자살로 인한 사망률을 줄이기 위한 정책 수립에 기초 자료로 활용될 수 있습니다. 18. 자살 예방 전략 및 프로그램 개발 시, 자살 방법에 대한 정보를 기반으로 효율적인 예방 전략을 수립해야 합니다. 19. 자살 시도자와 자살자의 유형을 이해함으로써, 유형별로 효과적인 자살 예방 전략을 마련할 필요가 있습니다. 20. 자살 예방을 위한 정책적 시사점으로는 농촌 거주 고령자의 자살 예방을 위해 살충제 등 치명적인 자살 수단의 관리 정책 도입이 필요합니다. 21. 자살 시도자들의 재시도 위험을 줄이기 위해 의료기관 내에서 적극적인 개입과 지원이 이루어져야 하며, 이를 위한 제도적 기반이 마련되어야 합니다. 22. 자살 예방 활동을 위한 의료인 교육 내용에 자살 시도자들의 특성을 반영하여, 반복 자살 시도를 예방할 수 있는 방안을 마련해야 합니다."
}