{
    "c_id": "33596_1",
    "domain": 2,
    "source": 1,
    "source_spec": "KJM",
    "creation_year": "2010",
    "content": "1. 1970년 이전까지 우리나라의 기생충 감염률은 매우 높았으며, 1949년 조사에서는 회충란 양성 비율이 82.8%에 달했습니다. 당시 인구 1인당 약 25마리의 회충을 보유한 것으로 추정되었습니다. 2. 1971년부터 전국적인 기생충 조사가 시작되면서 감염률이 점차 감소하여, 1992년 이후에는 4% 이하로 낮아졌습니다. 2013년 기준으로 전국 기생충 감염률은 2.6%로 보고되었으나, 이는 대변검사로 진단 가능한 기생충에 국한된 수치입니다. 3. 간흡충(Clonorchis sinensis)은 2013년 기준으로 1.9%의 감염률을 기록하며, 대변검사로 진단되는 기생충 중 가장 높은 감염률을 보였습니다. 감염은 주로 민물생선회를 통해 이루어지며, 낙동강 유역에서 감염률이 가장 높았습니다. 4. 간흡충 감염은 대개 무증상이지만, 중감염자에서는 상복부 통증, 황달, 설사 등의 증상이 나타날 수 있으며, 담도암과 같은 심각한 합병증을 유발할 수 있습니다. 간흡충 감염자는 담도암 스크리닝 검사가 권장됩니다. 5. 폐흡충(Paragonimus westermani)은 민물 게나 가재를 날로 섭취할 때 감염되며, 폐에 낭을 형성하여 호흡기 증상을 유발할 수 있습니다. 폐흡충은 뇌, 척수 등으로 이소기생할 수 있으며, 뇌 폐흡충증은 심각한 신경학적 증상을 초래할 수 있습니다. 6. 개회충(Toxocara canis)은 개가 종숙주로, 사람에게 감염되면 유충이 여러 장기를 침범하여 유충내장이행증을 일으킬 수 있습니다. 개회충 감염은 눈, 간, 뇌 등에서 다양한 증상을 유발하며, 알벤다졸이 치료에 효과적입니다. 7. 요충(Enterobius vermicularis)은 사람 간 접촉으로 전파되며, 주로 어린이에게 감염됩니다. 요충 감염은 항문 주위 가려움증을 유발하며, 구충제로 치료가 가능하지만 재감염 방지를 위해 가족 전체가 치료를 받아야 합니다. 8. 고래회충(Anisakis simplex)은 해산어류를 날로 섭취할 때 감염되며, 위벽을 뚫고 심한 복통과 구토를 유발할 수 있습니다. 위내시경으로 충체를 제거하여 진단과 치료가 가능합니다. 9. 편충(Trichuris trichiura)은 맹장에 기생하며, 감염 시 복통, 점혈변 등의 증상을 유발할 수 있습니다. 대장내시경이 진단에 유용하며, 알벤다졸이 치료에 효과적입니다. 10. 선모충(Trichinella spiralis)은 조리되지 않은 돼지고기나 야생동물 고기를 섭취할 때 감염되며, 근육통, 고열, 눈 주위 부종 등의 증상을 유발합니다. 메벤다졸이 치료에 효과적입니다. 11. 간질(Fasciola hepatica)은 간을 침범하여 우상복부 통증, 황달 등의 증상을 유발하며, triclobendazole이 치료에 효과적입니다. 12. 광절열두조충(Diphyllobothrium latum)은 담수어를 날로 섭취할 때 감염되며, 대변검사나 대장내시경으로 진단할 수 있습니다. 프라지판텔이 치료에 효과적입니다. 13. 스파르가눔(Sparganum)은 뱀이나 개구리를 날로 섭취하거나 오염된 물을 통해 감염되며, 피부나 중추신경계를 침범할 수 있습니다. 수술로 충체를 제거하는 것이 가장 효과적인 치료법입니다. 14. 유구낭미충(Cysticercus cellulosae)은 돼지고기를 덜 익혀 먹을 때 감염되며, 뇌를 침범하면 간질, 두통 등의 증상을 유발할 수 있습니다. 알벤다졸이 치료에 효과적입니다. 15. 아시아조충(Taenia asiatica)은 돼지의 간과 내장을 덜 익혀 먹을 때 감염되며, 프라지판텔로 치료가 가능합니다. 16. 단방조충(Echinococcus granulosus)은 개를 통해 전파되며, 간이나 폐에 포충을 형성하여 장기를 압박하는 증상을 유발할 수 있습니다. 수술이나 알벤다졸로 치료할 수 있습니다. 17. 말라리아(Malaria)는 열원충에 의해 발생하며, 우리나라에서는 삼일열원충(Plasmodium vivax)이 주로 보고됩니다. 클로로퀸과 프리마퀸이 치료에 사용됩니다. 18. 와포자충(Cryptosporidium spp.)은 수양성 설사를 유발하며, 면역저하자에서는 심각한 합병증을 초래할 수 있습니다. 특별한 치료법은 없으며, 수분공급이 중요합니다. 19. 톡소포자충(Toxoplasma gondii)은 돼지고기나 고양이 분변을 통해 감염되며, 면역저하자나 임신부에서는 심각한 합병증을 유발할 수 있습니다. 피리메타민과 설파디아진이 치료에 사용됩니다. 20. 우리나라의 기생충 감염률은 대변검사로 진단 가능한 기생충에 국한된 수치로, 실제 감염률은 더 높을 가능성이 있습니다. 기생충 질환에 대한 관심과 정확한 진단이 필요합니다."
}