{
    "c_id": "32375_1",
    "domain": 2,
    "source": 1,
    "source_spec": "KJM",
    "creation_year": "2005",
    "content": "자궁경부암은 전 세계적으로 유방암에 이어 두 번째로 흔한 여성 암으로, 최근 자궁경부 세포진 검사(Papanicolaou smear)를 통해 조기 검진이 가능해지면서 발생률이 감소하고 있습니다. 그러나 효과적인 화학요법 및 방사선 치료에도 불구하고 약 30%의 환자에서 질환의 지속이나 재발로 인해 사망하는 것으로 보고되고 있습니다. 자궁경부암의 재발은 주로 골반 내 병변 및 림프절 종대로 나타나는 국소 전이가 많지만, 복강 내 장기, 폐, 간, 뼈, 림프절 등으로 원격 전이가 발생할 수도 있습니다. 원격 전이는 전체 자궁경부암 환자의 약 4-10%에서 보고되며, 대부분 국소 재발과 함께 나타납니다. 원격 전이 중 가장 흔한 형태는 폐결절로, 흉곽 내 전이를 보이는 환자의 약 71%에서 관찰됩니다. 이 외에도 종격동 및 폐문 림프절 종대(32%), 흉막 전이(27%), 드물게 기관지 폐쇄(5%) 및 림프관 암종증(3%) 등이 보고됩니다. 본 증례는 자궁경부 선암종으로 수술 및 항암·방사선 치료를 받은 후 3년 뒤 호흡곤란을 주소로 내원한 54세 여성 환자입니다. 환자는 좌측 흉수를 동반한 흉막 종괴를 보였으며, 원발 병소의 재발 없이 흉막 전이로만 나타난 드문 사례로 진단되었습니다. 환자는 3년 전 자궁경부암으로 광범위 자궁적출술을 시행받았고, 이후 paclitaxel과 carboplatin 병합 항암요법 및 방사선 치료를 받았습니다. 내원 당시 흉부 단순 방사선 촬영과 흉부 컴퓨터단층촬영에서 좌측 흉수와 흉막 결절이 관찰되었습니다. 흉수천자 검사에서는 혈성 흉수와 삼출액 소견이 확인되었으며, 악성 세포는 관찰되지 않았습니다. 이후 흉강경을 이용한 흉막 종괴의 쐐기 절제술을 통해 병리학적으로 분화도가 낮은 전이성 선암종으로 진단되었습니다. 면역조직화학 염색 결과 CK20 양성, CK7 양성, TTF-1 음성으로 전이성 선암종에 합당한 소견을 보였습니다. 자궁경부암은 주로 림프관을 통해 원격 전이를 일으키며, 혈행 전이는 대동맥을 통해 폐실질 및 전신으로 퍼져나갑니다. 원격 전이의 흔한 부위는 폐, 대동맥 주위 림프절, 복강, 쇄골 상부 림프절 등이며, 흉막 전이는 매우 드문 경우에 해당합니다. 특히 선암종은 편평세포암보다 흉곽 내 전이가 더 흔하게 보고되며, 흉수를 동반하지 않는 림프절 종대가 특징적입니다. 본 환자는 자궁경부암의 원발 병소 재발 없이 흉막 전이만을 보인 비전형적인 사례로, 이는 매우 드문 경우에 해당합니다. 치료로는 cisplatin과 topotecan 병합 항암요법을 시행하였으며, 현재 흉수 및 전이 소견 없이 외래에서 추적 관찰 중입니다. 자궁경부암의 재발을 조기에 발견하기 위해 양전자단층촬영술(F-FDG PET/CT)이 효과적인 것으로 알려져 있으며, 이는 해부학적 변화뿐만 아니라 병변의 대사적 변화를 확인할 수 있어 유용합니다. 또한, 면역조직화학 염색법은 원발성 선암종과 전이성 선암종을 구별하는 데 도움을 줄 수 있습니다. 본 환자의 경우 CK20 양성, CK7 양성, TTF-1 음성 소견을 통해 전이성 선암종으로 진단할 수 있었습니다. 결론적으로, 본 증례는 자궁경부암의 원발 병소 재발 없이 흉막 전이만을 보인 드문 사례로, 자궁경부암의 비전형적인 전이 양상에 대한 이해를 높이는 데 기여할 수 있습니다."
}