{
    "c_id": "1392_1",
    "domain": 2,
    "source": 1,
    "source_spec": "guide_kr",
    "creation_year": "2023",
    "content": "1. 소아청소년 코로나19 확진자에서 스테로이드 투여는 임상적 효과와 안전성 측면에서 사망률, 급성 호흡부전 진행, 침습적 기계환기 필요성, 혈역학적 보조 치료 필요성에 어떤 영향을 미치는지 평가합니다. 또한 치료 시작 후 2일 이후 발열 지속 또는 재발, 심혈관계 기능 저하, 관상동맥 이상, 2차 치료 약제 사용 여부와 같은 중요한 임상적 결과를 포함하여 분석합니다. 2. 소아청소년 코로나19 확진자에서 렘데시비르 투여는 임상적 효과와 안전성 측면에서 사망률, 침습적 기계환기 필요성, 혈역학적 보조 치료 필요성에 어떤 영향을 미치는지 평가합니다. 또한 치료 시작 후 2일 이후 발열 지속 또는 재발, 심혈관계 기능 저하, 관상동맥 이상, 2차 치료 약제 사용 여부와 같은 중요한 임상적 결과를 포함하여 분석합니다. 3. 소아청소년 코로나19 확진자에서 토실리주맙 투여는 임상적 효과와 안전성 측면에서 사망률, 침습적 기계환기 필요성, 혈역학적 보조 치료 필요성에 어떤 영향을 미치는지 평가합니다. 또한 치료 시작 후 2일 이후 발열 지속 또는 재발, 심혈관계 기능 저하, 관상동맥 이상, 2차 치료 약제 사용 여부와 같은 중요한 임상적 결과를 포함하여 분석합니다. 4. 소아 다기관 염증증후군(MIS-C) 환자에서 정맥용 면역글로불린(IVIG)과 스테로이드 병용 투여는 IVIG 단독 투여와 비교하여 사망률, 중증 질환 발생, 침습적 기계환기 필요성, 혈역학적 보조 치료 필요성에 어떤 영향을 미치는지 평가합니다. 또한 치료 시작 후 2일 이후 발열 지속 또는 재발, 2차 치료 약제 사용 여부, 관상동맥 이상, 심혈관계 기능 저하, 입원 기간과 같은 중요한 임상적 결과를 포함하여 분석합니다. 5. 소아 다기관 염증증후군(MIS-C) 환자에서 스테로이드 단독 치료는 IVIG 단독 치료와 비교하여 사망률, 중증 질환 발생, 침습적 기계환기 필요성, 혈역학적 보조 치료 필요성에 어떤 영향을 미치는지 평가합니다. 또한 치료 시작 후 2일 이후 발열 지속 또는 재발, 2차 치료 약제 사용 여부, 관상동맥 이상, 심혈관계 기능 저하, 입원 기간과 같은 중요한 임상적 결과를 포함하여 분석합니다. 6. 소아 다기관 염증증후군(MIS-C) 환자에서 기타 면역조절제(인터루킨-1 억제제, 인터루킨-6 억제제, TNF 억제제)의 사용은 표준 치료와 비교하여 사망률, 침습적 기계환기 필요성, 혈역학적 보조 치료 필요성에 어떤 영향을 미치는지 평가합니다. 또한 퇴원 시 심장동맥류, 심혈관계 기능의 변화, 치료 시작 후 2일 이후 임상적 회복, 치료 시작 후 48시간 이상 발열 지속 여부와 같은 중요한 임상적 결과를 포함하여 분석합니다. 7. 소아 다기관 염증증후군(MIS-C) 환자에서 아스피린 및 항응고요법의 사용은 표준 치료와 비교하여 사망률, 혈전 발생 예방 효과에 어떤 영향을 미치는지 평가합니다. 또한 임상적 회복, 퇴원 시 심장동맥류, 심혈관계 기능의 변화와 같은 중요한 임상적 결과를 포함하여 분석합니다."
}