{
    "c_id": "33274_1",
    "domain": 2,
    "source": 1,
    "source_spec": "KJM",
    "creation_year": "2008",
    "content": "1. 우리나라에서 간경변증은 주요 사망 원인 중 하나로, 간질환의 유병률이 높습니다. 2. 2008년과 2009년 통계에 따르면, 간질환으로 인한 사망률은 인구 10만 명당 각각 17.3명과 15.6명으로, 사망 원인 6위와 7위를 차지했습니다. 3. 우리나라 간경변증 환자의 주요 원인은 B형 간염바이러스에 의한 만성 간질환으로, 전체 환자의 48-70%를 차지합니다. 4. 그 외 알코올성 간질환과 C형 간염바이러스에 의한 간질환이 주요 원인으로 나타납니다. 5. 간경변증의 합병증인 복수, 식도정맥류 출혈, 간성뇌증이 발생한 경우, 5년 생존율은 각각 32%, 21%, 40%로 매우 낮아 예후가 불량합니다. 6. 따라서 합병증을 동반한 비대상성 간경변증 환자에 대한 세심한 관리가 임상의에게 중요합니다. 7. 간경변증은 우리나라에서 대표적인 중증 간질환으로, 국내 의료 환경에 적합한 한국형 진료 가이드라인이 필요합니다. 8. 대한간학회는 2005년에 간경변증의 대표적 합병증인 복수, 정맥류 출혈, 간성뇌증의 치료 가이드라인을 제시했으나, 7년이 지난 현재 새로운 근거를 바탕으로 한 개정이 필요하다고 판단했습니다. 9. 이에 따라 대한간학회와 보건복지부 지정 간경변증 임상연구센터는 다학제적 접근을 통해 근거 중심의 간경변증 진료 가이드라인을 마련했습니다. 10. 이 가이드라인은 국내 보건의료인과 관련자들에게 간경변증 진료, 교육, 연구에 참고가 되도록 설계되었으며, 근거 중심 의학을 최우선으로 반영했습니다. 11. 가이드라인의 보건의료 범주는 간경변증의 진단 및 치료, 주요 합병증인 정맥류, 복수, 간성뇌증의 예방 및 관리에 관한 내용을 포함합니다. 12. 이 가이드라인은 간경변증 환자를 진료하는 보건의료인과 관련자, 그리고 간경변증으로 의료 서비스를 제공받아야 하는 모든 환자군을 대상으로 합니다. 13. 가이드라인의 기대 효과는 간경변증 환자의 합병증 치료 및 예방, 효과적인 관리 방법 제공, 보건의료인의 근거 중심 진료 정보 제공, 보건의료 정책에 대한 정보 제공, 국민 보건의료 수준 향상입니다. 14. 가이드라인 개정 과정은 내과학, 병리학, 영상의학, 예방의학 분야의 전문가들로 구성된 위원회가 주도했으며, 진단, 치료, 정맥류, 복수, 뇌증 등 세부 과제를 구분하여 진행되었습니다. 15. 2005년부터 2012년까지 여러 단계의 연구와 합의 과정을 거쳐 가이드라인이 개정되었습니다. 16. 가이드라인의 권고 사항은 GRADE 시스템에 따라 근거 수준과 권고 등급을 분류하여 제시되었습니다. 17. 간경변증 진단을 위해 병력 청취와 신체 진찰을 통해 간경변증의 소견을 확인하며, 말초혈액 검사, 간기능 검사, 영상 검사, 상부위장관 내시경 검사를 시행합니다. 18. 간경변증의 원인을 확인하기 위해 B형 및 C형 간염 검사를 시행하며, 중증도 평가는 Child-Pugh 등급 및 점수를 사용합니다. 19. 간경변증의 영상 검사에서는 간의 형태학적 변화와 복수, 문맥압 항진 소견을 확인합니다. 20. 간생검은 간경변증이 의심되나 검사 소견이 확정적이지 않을 경우 시행할 수 있습니다. 21. 간경변증 환자에서 원인에 따른 항섬유화 치료를 권장하며, B형 간염 환자는 항바이러스 치료를, C형 간염 환자는 페그인터페론과 리바비린 병합요법을 시행할 수 있습니다. 22. 알코올성 간경변증 환자는 금주가 필수적이며, 비알코올성 지방간질환 환자는 체중 감량, 식이요법, 운동 등 생활습관 개선이 필요합니다. 23. 원발성 담즙성 간경변증 환자에게는 ursodeoxycholic acid 투여를 권장합니다. 24. 간경변증 환자는 정맥류 출혈 예방을 위해 내시경 검사와 비선택적 베타차단제 사용을 고려합니다. 25. 급성 식도정맥류 출혈 환자는 혈관수축제와 항생제 치료를 병행하며, 내시경 치료를 권장합니다. 26. 간경변성 복수 환자는 염분 섭취를 제한하고, 이뇨제를 사용하며, 필요 시 대량복수 천자를 시행합니다. 27. 난치성 복수 환자는 반복적인 대량복수 천자나 경정맥 간내문맥전신 단락술을 고려하며, 간이식을 권장할 수 있습니다. 28. 간성뇌증 환자는 lactulose, rifaximin, L-ornithine-L-aspartate 등을 사용하며, 단백질 섭취를 조절합니다. 29. 간성뇌증이 발생한 환자는 재발 방지를 위해 비흡수성 이당류나 rifaximin을 투여할 수 있습니다. 30. 간경변증 환자에서 자발성 세균성 복막염이 의심되면 복수 천자와 항생제 치료를 시행하며, 예방적 항생제 사용을 고려할 수 있습니다. 31. 본 가이드라인은 근거 중심 의학에 기반하여 작성되었으며, 진료 과정에서 의사들의 결정의 질을 향상시키고 국민 보건의료 수준을 높이는 데 기여할 것입니다."
}